<?xml version="1.0" encoding="UTF-8"?>
<con:testCase id="10137fb8-6045-42dc-a58b-f99b937cf98a" failOnError="true" failTestCaseOnErrors="true" keepSession="false" maxResults="0" name="memberuid" searchProperties="true" xmlns:con="http://eviware.com/soapui/config"><con:settings/><con:testStep type="datasource" name="DataSource" id="c9f377bb-3aa5-42e1-93e1-4cf3ac5f3f7d" disabled="true"><con:settings/><con:config xsi:type="con:DataSourceStep" xmlns:xsi="http://www.w3.org/2001/XMLSchema-instance"><con:dataSource type="Excel"><con:configuration><file>C:/Users/faisal/Downloads/SOAP Projects/Member-Registration/memberuid.xlsx</file><worksheet>data</worksheet><cell>A2</cell><ignoreEmpty>false</ignoreEmpty></con:configuration></con:dataSource><con:property>username</con:property><con:property>password</con:property><con:property>gender</con:property><con:property>dob</con:property><con:property>nationality</con:property><con:property>passport</con:property><con:restartOnRun>true</con:restartOnRun></con:config></con:testStep><con:testStep type="request" id="67b63fd8-dfff-4ecf-be5e-a9f320e4f43d" name="ValidateMemberUID" disabled="true"><con:settings/><con:config xsi:type="con:RequestStep" xmlns:xsi="http://www.w3.org/2001/XMLSchema-instance"><con:interface>basicEndpoint</con:interface><con:operation>ValidateMemberUID</con:operation><con:request name="ValidateMemberUID" outgoingWss="" incomingWss="" timeout="" sslKeystore="" useWsAddressing="false" useWsReliableMessaging="false" wssPasswordType="" id="59c96011-24e9-4089-a8ff-472cbe83eb85"><con:settings><con:setting id="com.eviware.soapui.impl.wsdl.WsdlRequest@request-headers">&lt;xml-fragment/></con:setting></con:settings><con:encoding>UTF-8</con:encoding><con:endpoint>https://mr.eclaimlink.ae/MemberRegistration.svc/basic</con:endpoint><con:request><![CDATA[<soapenv:Envelope xmlns:soapenv="http://schemas.xmlsoap.org/soap/envelope/" xmlns:tem="http://tempuri.org/">
   <soapenv:Header/>
   <soapenv:Body>
      <tem:ValidateMemberUID>
         <!--Optional:-->
         <tem:payerLogin>${DataSource#username}</tem:payerLogin>
         <!--Optional:-->
         <tem:payerPwd>${DataSource#password}</tem:payerPwd>
         <!--Optional:-->
         
         <!--Optional:-->
         <tem:gender>${DataSource#gender}</tem:gender><tem:dateOfBirth>${DataSource#dob}</tem:dateOfBirth>
         <!--Optional:-->
         <tem:nationality>${DataSource#nationality}</tem:nationality>
         <!--Optional:-->
         <tem:passportNumber>${DataSource#passport}</tem:passportNumber><tem:visaSource>1</tem:visaSource>
         <!--Optional:-->
         
      </tem:ValidateMemberUID>
   </soapenv:Body>
</soapenv:Envelope>]]></con:request><con:assertion type="SOAP Response" id="163143b2-1ee0-4974-b7e4-8ed90c947107" name="SOAP Response"/><con:credentials><con:authType>No Authorization</con:authType></con:credentials><con:jmsConfig JMSDeliveryMode="PERSISTENT"/><con:jmsPropertyConfig/><con:wsaConfig mustUnderstand="NONE" version="200508" action="http://tempuri.org/IMemberRegistration/ValidateMemberUID"/><con:wsrmConfig version="1.2"/></con:request></con:config></con:testStep><con:testStep type="datasink" name="DataSink" id="b74dc6ad-0566-4f73-b378-e8e2dd8de664" disabled="true"><con:settings/><con:config xsi:type="con:DataSinkStep" xmlns:xsi="http://www.w3.org/2001/XMLSchema-instance"><con:dataSink type="Excel"><con:configuration><file>C:/Users/faisal/Downloads/SOAP Projects/Member-Registration/memberuid.xlsx</file><outfile>C:/Users/faisal/Downloads/SOAP Projects/Member-Registration/memberuid.xlsx</outfile><worksheet>result</worksheet><cell>A2</cell></con:configuration></con:dataSink><con:properties><con:property><con:name>code</con:name><con:value>${ValidateMemberUID#Response#declare namespace tem='http://tempuri.org/'; declare namespace mem='http://schemas.datacontract.org/2004/07/MemberRegistration'; //tem:ValidateMemberUIDResponse[1]/tem:ValidateMemberUIDResult[1]/mem:Result[1]}</con:value></con:property><con:property><con:name>description</con:name><con:value>${ValidateMemberUID#Response#declare namespace tem='http://tempuri.org/'; declare namespace mem='http://schemas.datacontract.org/2004/07/MemberRegistration'; //tem:ValidateMemberUIDResponse[1]/tem:ValidateMemberUIDResult[1]/mem:UID[1]}</con:value></con:property><con:property><con:name>error</con:name><con:value>${ValidateMemberUID#Response#declare namespace tem='http://tempuri.org/'; declare namespace mem='http://schemas.datacontract.org/2004/07/MemberRegistration'; //tem:ValidateMemberUIDResponse[1]/tem:ValidateMemberUIDResult[1]/mem:ErrorMessage[1]}</con:value></con:property></con:properties></con:config></con:testStep><con:testStep type="datasource" name="Copy of DataSource" id="c581c514-7e5f-41c1-9749-c4a7fdebda8a"><con:settings/><con:config xsi:type="con:DataSourceStep" xmlns:xsi="http://www.w3.org/2001/XMLSchema-instance"><con:dataSource type="File"><con:configuration><fileName>C:/Users/faisal/Downloads/SOAP Projects/Member-Registration/member_1M - 1.csv</fileName><separator>,</separator><trim>true</trim><charset>Cp1252</charset><quotedValues>false</quotedValues></con:configuration></con:dataSource><con:property>senderid</con:property><con:property>username</con:property><con:property>password</con:property><con:property>gender</con:property><con:property>dob</con:property><con:property>nationaltiy</con:property><con:property>passport</con:property><con:restartOnRun>true</con:restartOnRun></con:config></con:testStep><con:testStep type="request" id="50791505-4834-42ea-b7b8-439b413dbe2f" name="Copy of ValidateMemberUID"><con:settings/><con:config xsi:type="con:RequestStep" xmlns:xsi="http://www.w3.org/2001/XMLSchema-instance"><con:interface>basicEndpoint</con:interface><con:operation>ValidateMemberUID</con:operation><con:request name="Copy of ValidateMemberUID" outgoingWss="" incomingWss="" timeout="" sslKeystore="" useWsAddressing="false" useWsReliableMessaging="false" wssPasswordType="" id="59c96011-24e9-4089-a8ff-472cbe83eb85"><con:settings><con:setting id="com.eviware.soapui.impl.wsdl.WsdlRequest@request-headers">&lt;xml-fragment/></con:setting></con:settings><con:encoding>UTF-8</con:encoding><con:endpoint>https://mr.eclaimlink.ae/MemberRegistration.svc/basic</con:endpoint><con:request><![CDATA[<soapenv:Envelope xmlns:soapenv="http://schemas.xmlsoap.org/soap/envelope/" xmlns:tem="http://tempuri.org/">
   <soapenv:Header/>
   <soapenv:Body>
      <tem:ValidateMemberUID>
         <!--Optional:-->
         <tem:payerLogin>${Copy of DataSource#username}</tem:payerLogin>
         <!--Optional:-->
         <tem:payerPwd>${Copy of DataSource#password}</tem:payerPwd>
         <!--Optional:-->
         
         <!--Optional:-->
         <tem:gender>${Copy of DataSource#gender}</tem:gender><tem:dateOfBirth>${Copy of DataSource#dob}</tem:dateOfBirth>
         <!--Optional:-->
         <tem:nationality>${Copy of DataSource#nationaltiy}</tem:nationality>
         <!--Optional:-->
         <tem:passportNumber>${Copy of DataSource#passport}</tem:passportNumber><tem:visaSource>1</tem:visaSource>
         <!--Optional:-->
         
      </tem:ValidateMemberUID>
   </soapenv:Body>
</soapenv:Envelope>]]></con:request><con:assertion type="SOAP Response" id="163143b2-1ee0-4974-b7e4-8ed90c947107" name="SOAP Response"/><con:credentials><con:authType>No Authorization</con:authType></con:credentials><con:jmsConfig JMSDeliveryMode="PERSISTENT"/><con:jmsPropertyConfig/><con:wsaConfig mustUnderstand="NONE" version="200508" action="http://tempuri.org/IMemberRegistration/ValidateMemberUID"/><con:wsrmConfig version="1.2"/></con:request></con:config></con:testStep><con:testStep type="groovy" name="Groovy Script" id="bedd7750-fda4-436d-9232-f9df6772e0d7"><con:settings/><con:config><script>import groovy.xml.MarkupBuilder
import org.custommonkey.xmlunit.*
import java.util.Random  
import java.security.MessageDigest
import java.nio.file.*

def groovyUtils = new com.eviware.soapui.support.GroovyUtils(context)
	def projectPath = groovyUtils.projectPath
	def project = testRunner.testCase.testSuite.project
	def myTestSuite = testRunner.testCase.testSuite;
	def testCase = testRunner.testCase
	def testStepUploadDataAfterCheck = testCase.getTestStepByName("Copy of ValidateMemberUID")
	def time = testRunner.testCase.getTestStepByName("Copy of ValidateMemberUID").testRequest.response.timeTaken
	testRunner.testCase.getTestStepByName("responsetime").getProperty("rtime").setValue(time.toString())</script></con:config></con:testStep><con:testStep type="properties" name="responsetime" id="387ff1a4-b9d9-4085-a2f2-128ac2a58bf4"><con:settings/><con:config xsi:type="con:PropertiesStep" saveFirst="true" xmlns:xsi="http://www.w3.org/2001/XMLSchema-instance"><con:properties><con:property><con:name>rtime</con:name><con:value>4506</con:value></con:property></con:properties></con:config></con:testStep><con:testStep type="datasink" name="Copy of DataSink" id="72106c06-27a3-4eb4-94b0-5c7123391cfa"><con:settings/><con:config xsi:type="con:DataSinkStep" xmlns:xsi="http://www.w3.org/2001/XMLSchema-instance"><con:dataSink type="File"><con:configuration><fileName>C:/Users/faisal/Downloads/SOAP Projects/Member-Registration/result.csv</fileName><separator>,</separator><quote>true</quote><trim>true</trim><append>false</append><encoding>Cp1252</encoding></con:configuration></con:dataSink><con:properties><con:property><con:name>userid</con:name><con:value>${Copy of ValidateMemberUID#Request#declare namespace tem='http://tempuri.org/'; //tem:ValidateMemberUID[1]/tem:payerLogin[1]}</con:value></con:property><con:property><con:name>password</con:name><con:value>${Copy of ValidateMemberUID#Request#declare namespace tem='http://tempuri.org/'; //tem:ValidateMemberUID[1]/tem:payerPwd[1]}</con:value></con:property><con:property><con:name>gender</con:name><con:value>${Copy of ValidateMemberUID#Request#declare namespace tem='http://tempuri.org/'; //tem:ValidateMemberUID[1]/tem:gender[1]}</con:value></con:property><con:property><con:name>dob</con:name><con:value>${Copy of ValidateMemberUID#Request#declare namespace tem='http://tempuri.org/'; //tem:ValidateMemberUID[1]/tem:dateOfBirth[1]}</con:value></con:property><con:property><con:name>nationality</con:name><con:value>${Copy of ValidateMemberUID#Request#declare namespace tem='http://tempuri.org/'; //tem:ValidateMemberUID[1]/tem:nationality[1]}</con:value></con:property><con:property><con:name>passport</con:name><con:value>${Copy of ValidateMemberUID#Request#declare namespace tem='http://tempuri.org/'; //tem:ValidateMemberUID[1]/tem:passportNumber[1]}</con:value></con:property><con:property><con:name>resultcode</con:name><con:value>${Copy of ValidateMemberUID#Response#declare namespace tem='http://tempuri.org/'; declare namespace mem='http://schemas.datacontract.org/2004/07/MemberRegistration'; //tem:ValidateMemberUIDResponse[1]/tem:ValidateMemberUIDResult[1]/mem:Result[1]}</con:value></con:property><con:property><con:name>resultUID</con:name><con:value>${Copy of ValidateMemberUID#Response#declare namespace tem='http://tempuri.org/'; declare namespace mem='http://schemas.datacontract.org/2004/07/MemberRegistration'; //tem:ValidateMemberUIDResponse[1]/tem:ValidateMemberUIDResult[1]/mem:UID[1]}</con:value></con:property><con:property><con:name>errormessage</con:name><con:value>${Copy of ValidateMemberUID#Response#declare namespace tem='http://tempuri.org/'; declare namespace mem='http://schemas.datacontract.org/2004/07/MemberRegistration'; //tem:ValidateMemberUIDResponse[1]/tem:ValidateMemberUIDResult[1]/mem:ErrorMessage[1]}</con:value></con:property><con:property><con:name>timetaken</con:name><con:value>${responsetime#rtime}</con:value></con:property></con:properties></con:config></con:testStep><con:testStep type="datasourceloop" name="DataSource Loop" id="f9f0c0f6-a649-4625-9de5-3423ab4da50f"><con:settings/><con:config><dataSourceStep>Copy of DataSource</dataSourceStep><targetStep>Copy of ValidateMemberUID</targetStep></con:config></con:testStep><con:properties/><con:reportParameters/><con:breakPoints><con:testStepId>c9f377bb-3aa5-42e1-93e1-4cf3ac5f3f7d</con:testStepId><con:status>NONE</con:status><con:properties/></con:breakPoints><con:breakPoints><con:testStepId>c581c514-7e5f-41c1-9749-c4a7fdebda8a</con:testStepId><con:status>NONE</con:status><con:properties/></con:breakPoints><con:breakPoints><con:testStepId>72106c06-27a3-4eb4-94b0-5c7123391cfa</con:testStepId><con:status>NONE</con:status><con:properties/></con:breakPoints><con:breakPoints><con:testStepId>67b63fd8-dfff-4ecf-be5e-a9f320e4f43d</con:testStepId><con:status>NONE</con:status><con:properties/></con:breakPoints><con:breakPoints><con:testStepId>b74dc6ad-0566-4f73-b378-e8e2dd8de664</con:testStepId><con:status>NONE</con:status><con:properties/></con:breakPoints><con:breakPoints><con:testStepId>50791505-4834-42ea-b7b8-439b413dbe2f</con:testStepId><con:status>NONE</con:status><con:properties/></con:breakPoints></con:testCase>